onlyocr/__init__.py
onlyocr-1.0.0.dist-info/LICENSE.txt
onlyocr-1.0.0.dist-info/METADATA
onlyocr-1.0.0.dist-info/WHEEL
onlyocr-1.0.0.dist-info/top_level.txt
onlyocr-1.0.0.dist-info/RECORD
