Metadata-Version: 2.1
Name: onlyocr
Version: 1.0.0
Summary: UNKNOWN
Home-page: UNKNOWN
Author: Devaloy Mukherjee
Author-email: devaloy.mukherjee@gmail.com
License: UNKNOWN
Platform: UNKNOWN
